{"Domain":0,"Client":0,"Weight":1.0}
{"Domain":1,"Client":1,"Weight":1.0}
{"Domain":1,"Client":29,"Weight":0.1}
{"Domain":2,"Client":2,"Weight":5.3333333333}
{"Domain":2,"Client":3,"Weight":5.0}
{"Domain":2,"Client":9,"Weight":1.3333333333}
{"Domain":2,"Client":29,"Weight":0.2}
{"Domain":2,"Client":37,"Weight":1.0}
{"Domain":2,"Client":38,"Weight":1.0}
{"Domain":2,"Client":41,"Weight":1.0}
{"Domain":2,"Client":42,"Weight":0.6666666667}
{"Domain":3,"Client":4,"Weight":0.5}
{"Domain":4,"Client":5,"Weight":1.0}
{"Domain":5,"Client":6,"Weight":1.0}
{"Domain":5,"Client":11,"Weight":1.0}
{"Domain":6,"Client":7,"Weight":1.0}
{"Domain":7,"Client":8,"Weight":1.0}
{"Domain":8,"Client":9,"Weight":0.3333333333}
{"Domain":8,"Client":10,"Weight":1.0}
{"Domain":8,"Client":20,"Weight":16.0}
{"Domain":8,"Client":21,"Weight":16.0}
{"Domain":8,"Client":22,"Weight":16.0}
{"Domain":8,"Client":23,"Weight":16.0}
{"Domain":8,"Client":24,"Weight":16.0}
{"Domain":8,"Client":25,"Weight":16.0}
{"Domain":8,"Client":26,"Weight":16.0}
{"Domain":8,"Client":27,"Weight":16.0}
{"Domain":8,"Client":28,"Weight":1.0}
{"Domain":8,"Client":35,"Weight":1.0}
{"Domain":8,"Client":44,"Weight":2.0}
{"Domain":8,"Client":45,"Weight":1.0}
{"Domain":8,"Client":46,"Weight":2.0}
{"Domain":9,"Client":12,"Weight":1.0}
{"Domain":10,"Client":13,"Weight":1.0}
{"Domain":11,"Client":14,"Weight":1.0}
{"Domain":11,"Client":42,"Weight":2.0}
{"Domain":12,"Client":4,"Weight":0.5}
{"Domain":13,"Client":15,"Weight":1.3333333333}
{"Domain":14,"Client":16,"Weight":1.0}
{"Domain":15,"Client":17,"Weight":1.0}
{"Domain":16,"Client":18,"Weight":2.0}
{"Domain":17,"Client":19,"Weight":2.0}
{"Domain":17,"Client":29,"Weight":0.2}
{"Domain":18,"Client":29,"Weight":0.1}
{"Domain":18,"Client":33,"Weight":1.0}
{"Domain":19,"Client":30,"Weight":5.0}
{"Domain":19,"Client":31,"Weight":5.0}
{"Domain":20,"Client":32,"Weight":1.0}
{"Domain":21,"Client":15,"Weight":0.3333333333}
{"Domain":22,"Client":34,"Weight":1.0}
{"Domain":23,"Client":14,"Weight":1.3333333333}
{"Domain":24,"Client":36,"Weight":0.5}
{"Domain":25,"Client":39,"Weight":1.0}
{"Domain":26,"Client":40,"Weight":1.0}
{"Domain":27,"Client":29,"Weight":0.1}
{"Domain":28,"Client":29,"Weight":0.1}
{"Domain":29,"Client":29,"Weight":0.1}
{"Domain":30,"Client":29,"Weight":0.1}
{"Domain":31,"Client":29,"Weight":0.1}
{"Domain":32,"Client":29,"Weight":0.1}
{"Domain":33,"Client":43,"Weight":1.0}
{"Domain":34,"Client":47,"Weight":1.0}
{"Domain":35,"Client":48,"Weight":1.0}
{"Domain":36,"Client":49,"Weight":1.0}
{"Domain":37,"Client":36,"Weight":0.5}
